pysqlite3tool/__init__.py
pysqlite3tool-0.0.1a0.dist-info/LICENSE
pysqlite3tool-0.0.1a0.dist-info/METADATA
pysqlite3tool-0.0.1a0.dist-info/WHEEL
pysqlite3tool-0.0.1a0.dist-info/top_level.txt
pysqlite3tool-0.0.1a0.dist-info/RECORD
