Metadata-Version: 2.1
Name: pysqlite3tool
Version: 0.0.1a0
Summary: The cross-platform tool to work with SQLite3 database
Home-page: https://github.com/c-pher/SQLite3Tool.git
Author: Andrey Komissarov
Author-email: a.komisssarov@gmail.com
License: MIT
Platform: UNKNOWN
Classifier: Programming Language :: Python :: 3
Classifier: License :: OSI Approved :: MIT License
Classifier: Operating System :: OS Independent
Classifier: Intended Audience :: System Administrators
Classifier: Intended Audience :: Developers
Classifier: Natural Language :: English
Classifier: Programming Language :: Python :: 3.7
Classifier: Topic :: System :: Systems Administration
Classifier: Topic :: Software Development :: Libraries :: Python Modules
Requires-Python: >=3.6
